apikcmd/__init__.py
apikcmd/core.py
apikcmd-0.1.0.dist-info/METADATA
apikcmd-0.1.0.dist-info/WHEEL
apikcmd-0.1.0.dist-info/top_level.txt
apikcmd-0.1.0.dist-info/RECORD
