Metadata-Version: 2.4
Name: apikcmd
Version: 0.1.0
Summary: A simple command interface for REST API CRUD operations
Home-page: https://github.com/yourusername/apikcmd
Author: KC
Classifier: Programming Language :: Python :: 3
Classifier: Operating System :: OS Independent
Requires-Python: >=3.6
Requires-Dist: requests
Dynamic: author
Dynamic: classifier
Dynamic: description
Dynamic: description-content-type
Dynamic: home-page
Dynamic: requires-dist
Dynamic: requires-python
Dynamic: summary
